password_generator_simon994/__init__.py
password_generator_simon994/password_generator_simon994.py
password_generator_simon994-0.0.5.dist-info/entry_points.txt
password_generator_simon994-0.0.5.dist-info/WHEEL
password_generator_simon994-0.0.5.dist-info/METADATA
password_generator_simon994-0.0.5.dist-info/RECORD
